{"nm":"Main Scene","ddd":0,"h":106,"w":148,"meta":{"g":"@lottiefiles/creator 1.31.1"},"layers":[{"ty":4,"nm":"Path 1","sr":1,"st":0,"op":150,"ip":0,"hd":false,"ddd":0,"bm":0,"hasMask":false,"ao":0,"ks":{"a":{"a":0,"k":[74,56]},"s":{"a":0,"k":[100,100]},"sk":{"a":0,"k":0},"p":{"a":0,"k":[74,56]},"r":{"a":0,"k":0},"sa":{"a":0,"k":0},"o":{"a":0,"k":100}},"shapes":[{"ty":"sh","bm":0,"hd":false,"nm":"PATH Shape Path 2","d":1,"ks":{"a":0,"k":{"c":false,"i":[[0,0],[-13.87934726968502,-9.37419993883288],[0,0],[-37.17898914663918,-12.968371059273068],[0,0]],"o":[[0.1419230580801525,-0.23653843013359221],[13.87934726968502,9.37419993883288],[0,0],[37.17898914663918,12.968371059273068],[0,0]],"v":[[7.001566506473267,25.06778307088128],[42.317360634214,15.089500372014925],[38.51091143544879,67.43120939901267],[98.6147200235997,40.17227810689926],[141.76660778550973,99.11280282582905]]}}},{"ty":"st","bm":0,"hd":false,"nm":"Stroke","lc":2,"lj":2,"ml":1,"o":{"a":0,"k":100},"w":{"a":0,"k":1.5},"c":{"a":0,"k":[0.9922,0.9412,0.902]}},{"ty":"tm","bm":0,"hd":false,"nm":"Trim Path","e":{"a":1,"k":[{"o":{"x":0.167,"y":0.167},"i":{"x":0.833,"y":0.833},"s":[100],"t":0},{"s":[100],"t":30}]},"o":{"a":0,"k":0},"s":{"a":1,"k":[{"o":{"x":0.167,"y":0.167},"i":{"x":0.833,"y":0.833},"s":[0],"t":0},{"s":[100],"t":30}]},"m":1}],"ind":1}],"v":"5.7.0","fr":30,"op":90,"ip":0,"assets":[]}